{"cameraMode":{"drawMode":0,"name":"Shaded","section":"Shading Mode"},"sceneLighting":false,"audioPlay":false,"sceneViewState":{"showFog":true,"showMaterialUpdate":false,"showSkybox":true,"showFlares":true,"showImageEffects":true,"showParticleSystems":true,"showVisualEffectGraphs":true,"m_FxEnabled":true},"in2DMode":false,"pivot":{"x":4.464371204376221,"y":0.8590657711029053,"z":18.196020126342775},"rotation":{"x":0.082326740026474,"y":0.04452092945575714,"z":-0.003705399576574564,"w":0.9955501556396484},"size":12.12435531616211,"orthographic":false}