{"cameraMode":{"drawMode":0,"name":"Shaded","section":"Shading Mode"},"sceneLighting":true,"audioPlay":false,"sceneViewState":{"showFog":true,"showMaterialUpdate":false,"showSkybox":true,"showFlares":true,"showImageEffects":true,"showParticleSystems":true,"showVisualEffectGraphs":true,"m_FxEnabled":true},"in2DMode":false,"pivot":{"x":13.070982933044434,"y":-2.9691619873046877,"z":-3.438386917114258},"rotation":{"x":0.0038318848237395288,"y":0.9501616358757019,"z":-0.3115130364894867,"w":0.011688655242323876},"size":10.0,"orthographic":false}